README.rst
setup.py
nec_pd_sdk/__init__.py
nec_pd_sdk/constants.py
nec_pd_sdk/controls.txt
nec_pd_sdk/nec_pd_sdk.py
nec_pd_sdk/opcode_decoding.py
nec_pd_sdk/protocol.py
nec_pd_sdk.egg-info/PKG-INFO
nec_pd_sdk.egg-info/SOURCES.txt
nec_pd_sdk.egg-info/dependency_links.txt
nec_pd_sdk.egg-info/requires.txt
nec_pd_sdk.egg-info/top_level.txt