Metadata-Version: 1.1
Name: nec-pd-sdk
Version: 17.4.61
Summary: NEC PD SDK
Home-page: https://github.com/necsoftware/necpdsdk
Author: NEC Display Solutions, Ltd.
Author-email: techsupport@necdisplay.com
License: MIT
Download-URL: https://github.com/NECDisplaySolutions/necpdsdk.git
Keywords: NEC pd sdk
Platform: UNKNOWN
Classifier: Development Status :: 3 - Alpha
Classifier: Intended Audience :: Developers
Classifier: Topic :: Software Development
Classifier: License :: OSI Approved :: MIT License
Classifier: Programming Language :: Python :: 2.7
